cognee_community_vector_adapter_azure/__init__.py
cognee_community_vector_adapter_azure/azureaisearch_adapter.py
cognee_community_vector_adapter_azure/register.py
cognee_community_vector_adapter_azure-1.0.0.dist-info/METADATA
cognee_community_vector_adapter_azure-1.0.0.dist-info/WHEEL
cognee_community_vector_adapter_azure-1.0.0.dist-info/RECORD
