Metadata-Version: 2.4
Name: cognee-community-vector-adapter-azure
Version: 1.0.0
Summary: Azure AI search vector database adapter for cognee
Project-URL: Homepage, https://www.cognee.ai
Project-URL: Repository, https://github.com/topoteretes/cognee-community
Requires-Python: <=3.13,>=3.10
Requires-Dist: azure-core>=1.29.0
Requires-Dist: azure-search-documents>=11.4.0
Requires-Dist: cognee>=0.1.41
